turbocrawler/__init__.py
turbocrawler/engine/__init__.py
turbocrawler/engine/base_queues/__init__.py
turbocrawler/engine/base_queues/crawled_queue_base.py
turbocrawler/engine/base_queues/crawler_queue_base.py
turbocrawler/engine/control.py
turbocrawler/engine/crawler.py
turbocrawler/engine/data_types/__init__.py
turbocrawler/engine/data_types/crawler.py
turbocrawler/engine/data_types/info.py
turbocrawler/engine/plugin.py
turbocrawler/engine/runners/__init__.py
turbocrawler/engine/runners/crawler_runner.py
turbocrawler/engine/runners/thread_runner.py
turbocrawler/engine/url_extractor.py
turbocrawler/engine/worker_queues.py
turbocrawler/log.txt
turbocrawler/logger.py
turbocrawler/parsers/__init__.py
turbocrawler/parsers/json_file_maker.py
turbocrawler/queues/__init__.py
turbocrawler/queues/crawled_queue.py
turbocrawler/queues/crawler_queues.py
turbocrawler/utils.py
turbocrawler-0.0.1.post1.dist-info/LICENSE
turbocrawler-0.0.1.post1.dist-info/METADATA
turbocrawler-0.0.1.post1.dist-info/WHEEL
turbocrawler-0.0.1.post1.dist-info/RECORD
