Metadata-Version: 2.1
Name: turbocrawler
Version: 0.0.1.post1
Summary: Scraping and Crawling Micro-Framework
Home-page: https://github.com/toriium/turbocrawler
License: MIT
Keywords: crawler,crawler framework,scraping,turbocrawler
Author: toriium
Requires-Python: >=3.11,<4.0
Classifier: License :: OSI Approved :: MIT License
Classifier: Programming Language :: Python :: 3
Classifier: Programming Language :: Python :: 3.11
Requires-Dist: parsel
Project-URL: Repository, https://github.com/toriium/turbocrawler
